pathdantic/__init__.py
pathdantic/base.py
pathdantic/file.py
pathdantic/folder.py
pathdantic/root.py
tests/__init__.py
pathdantic-0.0.2.dist-info/LICENSE
pathdantic-0.0.2.dist-info/METADATA
pathdantic-0.0.2.dist-info/WHEEL
pathdantic-0.0.2.dist-info/top_level.txt
pathdantic-0.0.2.dist-info/RECORD
