Metadata-Version: 2.1
Name: pathdantic
Version: 0.0.2
Home-page: https://pypi.org/project/pathdantic
Author: Alejo Prieto Dávalos
Author-email: alejoprietodavalos@gmail.com
Project-URL: Source, https://github.com/AlejoPrietoDavalos/pathdantic/
Requires-Python: >=3.10,<3.12
License-File: LICENSE
Requires-Dist: pydantic ==2.6.3
Requires-Dist: setuptools ==65.5.0
